{"prefix": {"vargen": "http://openprovenance.org/vargen#", "s-prov": "http://s-prov/ns/#", "pre_0": "http://www.w3.org/2001/XMLSchema", "dare": "http://project-dare.eu/ns#", "d-prov": "http://d-prov.org/#", "vcard": "http://www.w3.org/2006/vcard/ns#", "var": "http://openprovenance.org/var#", "tmpl": "http://openprovenance.org/tmpl#", "dcterms": "http://purl.org/dc/terms/", "foaf": "http://xmlns.com/foaf/0.1/"}, "bundle": {"var:Session": {"prefix": {"dare": "http://project-dare.eu/ns#", "vcard": "http://www.w3.org/2006/vcard/ns#", "var": "http://openprovenance.org/var#", "tmpl": "http://openprovenance.org/tmpl#", "dcterms": "http://purl.org/dc/terms/"}, "entity": {"var:K8Srecipe": {"prov:atLocation": {"$": "var:worker", "type": "prov:QUALIFIED_NAME"}, "prov:type": {"$": "dare:domainPlan", "type": "prov:QUALIFIED_NAME"}}, "var:lib": {"var:term_0": "var:n", "prov:type": {"$": "dare:lib", "type": "prov:QUALIFIED_NAME"}}, "var:libs": {"tmpl:linked": {"$": "var:lib", "type": "prov:QUALIFIED_NAME"}, "prov:type": {"$": "dare:LibCollection", "type": "prov:QUALIFIED_NAME"}}, "var:env": {"var:python": "var:version", "prov:type": {"$": "dare:Environment", "type": "prov:QUALIFIED_NAME"}}, "var:Jupyter": {"prov:type": {"$": "dare:Session", "type": "prov:QUALIFIED_NAME"}, "dcterms:url": {"$": "var:url", "type": "prov:QUALIFIED_NAME"}}}, "used": {"_:id1": {"prov:activity": "var:CreateSession", "prov:entity": "var:libs"}, "_:id2": {"prov:activity": "var:CreateSession", "prov:entity": "var:env"}}, "wasAssociatedWith": {"_:id3": {"prov:activity": "var:CreateSession", "prov:agent": "var:NotebookAPI", "prov:plan": "var:K8Srecipe"}}, "activity": {"var:CreateSession": {"prov:type": "dare:CreateSession", "prov:endTime": "1970-01-01T01:01:00+01:00", "prov:startTime": "1970-01-01T01:00:00+01:00"}}, "actedOnBehalfOf": {"_:id4": {"prov:delegate": "var:NotebookAPI", "prov:responsible": "var:user"}}, "agent": {"var:user": {"vcard:uid": "var:name", "prov:type": "prov:Person"}, "var:NotebookAPI": {"vcard:uid": "var:name_api", "prov:type": "prov:SoftwareAgent"}}, "wasGeneratedBy": {"_:id5": {"prov:activity": "var:CreateSession", "prov:entity": "var:Jupyter"}}, "hadMember": {"_:id6": {"prov:collection": "var:libs", "prov:entity": "var:lib"}}}}}